esp_lab/__init__.py
esp_lab/data_access.py
esp_lab/stats.py
esp_lab-1.1.1.dist-info/LICENSE
esp_lab-1.1.1.dist-info/METADATA
esp_lab-1.1.1.dist-info/WHEEL
esp_lab-1.1.1.dist-info/top_level.txt
esp_lab-1.1.1.dist-info/RECORD
