Metadata-Version: 2.1
Name: esp-lab
Version: 1.1.1
Summary: Utilities for SMYLE Analysis
Home-page: https://esp-lab.readthedocs.io
Maintainer: ESP-Lab Team
Maintainer-email: tking@ucar.edu
License: Apache 2.0
Project-URL: Documentation, https://esp-lab.readthedocs.io
Project-URL: Source, https://github.com/CESM-ESPWG/ESP-Lab
Project-URL: Tracker, https://github.com/CESM-ESPWG/ESP-Lab/issues
Keywords: ESP-Lab,SMYLE,Analysis,Earth System Predictions
Platform: UNKNOWN
Classifier: Development Status :: 4 - Beta
Classifier: License :: OSI Approved :: Apache Software License
Classifier: Operating System :: OS Independent
Classifier: Intended Audience :: Science/Research
Classifier: Programming Language :: Python
Classifier: Programming Language :: Python :: 3
Classifier: Programming Language :: Python :: 3.8
Classifier: Programming Language :: Python :: 3.9
Classifier: Programming Language :: Python :: 3.10
Classifier: Topic :: Scientific/Engineering
Requires-Python: >=3.8
License-File: LICENSE
